stack=2, locals=4, args_size=1
         0: sipush        1000
         3: istore_1
         4: sipush        1000
         7: invokestatic  #2                  // Method java/lang/Integer.valueOf:(I)Ljava/lang/Integer;
        10: astore_2
        11: iload_1
        12: aload_2
        13: invokevirtual #3                  // Method java/lang/Integer.intValue:()I
        16: if_icmpne     23
        19: iconst_1
        20: goto          24
        23: iconst_0
        24: istore_3
        25: return



stack=1, locals=3, args_size=1
         0: sipush        1000
         3: istore_1
         4: sipush        1000
         7: invokestatic  #2                  // Method java/lang/Integer.valueOf:(I)Ljava/lang/Integer;
        10: astore_2
        11: return
